{"members":[{"id":619,"username":"Allminoxy","avatar_template":"/user_avatar/forums.crateentertainment.com/allminoxy/{size}/349_2.png","primary_group_name":"Crate_Employee","title":"Crate Employee - Artist","last_posted_at":"2019-07-05T14:50:36.163Z","last_seen_at":"2019-07-09T19:05:43.055Z","added_at":"2019-06-06T04:38:46.268Z"},{"id":96,"username":"evil_medierra","avatar_template":"/user_avatar/forums.crateentertainment.com/evil_medierra/{size}/96_2.png","primary_group_name":"Crate_Employee","title":"Primordial Being","last_posted_at":null,"last_seen_at":"1969-12-31T19:00:00.000Z","added_at":"2019-06-07T04:25:49.855Z"},{"id":6270,"username":"Grava","avatar_template":"/user_avatar/forums.crateentertainment.com/grava/{size}/8032_2.png","primary_group_name":"Crate_Employee","title":"Crate Employee - Designer","last_posted_at":"2019-06-20T19:27:10.652Z","last_seen_at":"2019-06-20T19:48:38.167Z","added_at":"2019-06-06T04:38:46.268Z"},{"id":2025,"username":"Hyboreal","avatar_template":"/user_avatar/forums.crateentertainment.com/hyboreal/{size}/6881_2.png","primary_group_name":"Crate_Employee","title":"Crate Employee - Designer","last_posted_at":"2019-06-27T20:17:12.118Z","last_seen_at":"2019-07-09T19:00:29.722Z","added_at":"2019-06-06T04:38:46.268Z"},{"id":850,"username":"Kinree","avatar_template":"/user_avatar/forums.crateentertainment.com/kinree/{size}/1920_2.png","primary_group_name":"Crate_Employee","title":"Crate Employee - Programmer","last_posted_at":"2019-06-08T16:42:41.281Z","last_seen_at":"2019-07-09T16:34:03.980Z","added_at":"2019-06-06T04:38:46.268Z"},{"id":2,"username":"medierra","avatar_template":"/user_avatar/forums.crateentertainment.com/medierra/{size}/16_2.png","primary_group_name":"Crate_Employee","title":"Crate Employee - Designer","last_posted_at":null,"last_seen_at":"1969-12-31T19:00:00.000Z","added_at":"2019-06-07T04:25:49.796Z"},{"id":1,"username":"Rhis","avatar_template":"/user_avatar/forums.crateentertainment.com/rhis/{size}/6618_2.png","primary_group_name":"Crate_Employee","title":"Crate Employee - Programmer","last_posted_at":"2019-06-21T13:38:19.134Z","last_seen_at":"2019-07-06T21:30:10.487Z","added_at":"2019-06-07T04:25:49.869Z"},{"id":808,"username":"Sandcaster","avatar_template":"/user_avatar/forums.crateentertainment.com/sandcaster/{size}/427_2.png","primary_group_name":"Crate_Employee","title":"Crate Employee - Artist","last_posted_at":null,"last_seen_at":"2019-07-08T02:16:45.852Z","added_at":"2019-06-06T04:38:46.268Z"},{"id":36,"username":"Soundz","avatar_template":"/user_avatar/forums.crateentertainment.com/soundz/{size}/16_2.png","primary_group_name":"Crate_Employee","title":"Crate Employee - Sound / Music","last_posted_at":null,"last_seen_at":"1969-12-31T19:00:00.000Z","added_at":"2019-06-06T04:38:46.268Z"},{"id":1278,"username":"Westfaliah","avatar_template":"/user_avatar/forums.crateentertainment.com/westfaliah/{size}/6878_2.png","primary_group_name":"Crate_Employee","title":"Crate Employee - Programmer","last_posted_at":null,"last_seen_at":"2019-07-09T14:58:49.904Z","added_at":"2019-06-06T04:38:46.268Z"},{"id":538,"username":"Zantai","avatar_template":"/user_avatar/forums.crateentertainment.com/zantai/{size}/324_2.png","primary_group_name":"Crate_Employee","title":"Crate Employee - Designer","last_posted_at":"2019-07-09T17:23:45.510Z","last_seen_at":"2019-07-09T20:01:23.626Z","added_at":"2019-06-07T04:25:21.779Z"}],"owners":[],"meta":{"total":11,"limit":50,"offset":0}}