{"members":[{"id":619,"username":"Allminoxy","avatar_template":"/user_avatar/forums.crateentertainment.com/allminoxy/{size}/349_2.png","primary_group_name":"Crate_Employee","title":"Crate Employee - Artist","last_posted_at":"2019-07-05T14:50:36.163Z","last_seen_at":"2019-07-09T19:05:43.055Z","added_at":"2019-06-07T17:00:45.783Z"},{"id":16,"username":"eisprinzessin","avatar_template":"/user_avatar/forums.crateentertainment.com/eisprinzessin/{size}/8408_2.png","title":"Minister of Information","last_posted_at":"2019-07-09T12:21:54.128Z","last_seen_at":"2019-07-09T20:08:42.207Z","added_at":"2019-06-07T03:41:14.455Z"},{"id":867,"username":"EyesWideOpen84","avatar_template":"/user_avatar/forums.crateentertainment.com/eyeswideopen84/{size}/3383_2.png","title":"Super Moderator","last_posted_at":null,"last_seen_at":"1969-12-31T19:00:00.000Z","added_at":"2019-06-07T03:41:47.575Z"},{"id":8,"username":"Father_Squid","avatar_template":"/user_avatar/forums.crateentertainment.com/father_squid/{size}/24_2.png","title":"Super Moderator","last_posted_at":null,"last_seen_at":"2019-06-22T10:25:31.341Z","added_at":"2019-06-07T03:42:23.093Z"},{"id":6270,"username":"Grava","avatar_template":"/user_avatar/forums.crateentertainment.com/grava/{size}/8032_2.png","primary_group_name":"Crate_Employee","title":"Crate Employee - Designer","last_posted_at":"2019-06-20T19:27:10.652Z","last_seen_at":"2019-06-20T19:48:38.167Z","added_at":"2019-06-07T17:00:21.912Z"},{"id":2025,"username":"Hyboreal","avatar_template":"/user_avatar/forums.crateentertainment.com/hyboreal/{size}/6881_2.png","primary_group_name":"Crate_Employee","title":"Crate Employee - Designer","last_posted_at":"2019-06-27T20:17:12.118Z","last_seen_at":"2019-07-09T19:00:29.722Z","added_at":"2019-06-07T17:01:34.902Z"},{"id":5,"username":"jiaco","avatar_template":"/user_avatar/forums.crateentertainment.com/jiaco/{size}/19_2.png","title":"Super Moderator","last_posted_at":"2019-06-28T04:25:09.427Z","last_seen_at":"2019-07-05T16:23:35.909Z","added_at":"2019-06-07T03:42:36.257Z"},{"id":850,"username":"Kinree","avatar_template":"/user_avatar/forums.crateentertainment.com/kinree/{size}/1920_2.png","primary_group_name":"Crate_Employee","title":"Crate Employee - Programmer","last_posted_at":"2019-06-08T16:42:41.281Z","last_seen_at":"2019-07-09T16:34:03.980Z","added_at":"2019-06-07T17:01:58.109Z"},{"id":108,"username":"medea_fleecestealer","avatar_template":"/user_avatar/forums.crateentertainment.com/medea_fleecestealer/{size}/110_2.png","title":"Super Moderator","last_posted_at":"2019-07-09T19:21:33.212Z","last_seen_at":"2019-07-09T20:06:40.631Z","added_at":"2019-06-07T03:42:47.652Z"},{"id":2,"username":"medierra","avatar_template":"/user_avatar/forums.crateentertainment.com/medierra/{size}/16_2.png","primary_group_name":"Crate_Employee","title":"Crate Employee - Designer","last_posted_at":null,"last_seen_at":"1969-12-31T19:00:00.000Z","added_at":"2019-06-07T17:03:36.861Z"},{"id":1,"username":"Rhis","avatar_template":"/user_avatar/forums.crateentertainment.com/rhis/{size}/6618_2.png","primary_group_name":"Crate_Employee","title":"Crate Employee - Programmer","last_posted_at":"2019-06-21T13:38:19.134Z","last_seen_at":"2019-07-06T21:30:10.487Z","added_at":"2019-06-07T17:03:51.426Z"},{"id":808,"username":"Sandcaster","avatar_template":"/user_avatar/forums.crateentertainment.com/sandcaster/{size}/427_2.png","primary_group_name":"Crate_Employee","title":"Crate Employee - Artist","last_posted_at":null,"last_seen_at":"2019-07-08T02:16:45.852Z","added_at":"2019-06-07T17:04:03.590Z"},{"id":1278,"username":"Westfaliah","avatar_template":"/user_avatar/forums.crateentertainment.com/westfaliah/{size}/6878_2.png","primary_group_name":"Crate_Employee","title":"Crate Employee - Programmer","last_posted_at":null,"last_seen_at":"2019-07-09T14:58:49.904Z","added_at":"2019-06-07T17:04:40.485Z"},{"id":538,"username":"Zantai","avatar_template":"/user_avatar/forums.crateentertainment.com/zantai/{size}/324_2.png","primary_group_name":"Crate_Employee","title":"Crate Employee - Designer","last_posted_at":"2019-07-09T17:23:45.510Z","last_seen_at":"2019-07-09T20:01:23.626Z","added_at":"2019-06-07T17:04:58.845Z"}],"owners":[],"meta":{"total":14,"limit":50,"offset":0}}